Domoticzpy/Domoticzpy.py
Domoticzpy/__init__.py
Domoticzpy-0.1.8.dist-info/LICENSE
Domoticzpy-0.1.8.dist-info/METADATA
Domoticzpy-0.1.8.dist-info/WHEEL
Domoticzpy-0.1.8.dist-info/top_level.txt
Domoticzpy-0.1.8.dist-info/RECORD
